{
  "sections": {
    "main-collection": {
      "type": "main-collection",
      "settings": {
      }
    },
    "16484938648f5c52b0": {
      "type": "home-collection-row",
      "settings": {
        "collection_one": "headphones",
        "collection_two": "speakers",
        "collection_three": "earphones"
      }
    },
    "1648493869fde2feed": {
      "type": "home-about",
      "settings": {
        "image_mobile": "shopify:\/\/shop_images\/image-best-gear.jpg",
        "about_heading": "Bringing you the best audio gear",
        "about_copy": "<p>Located at the heart of New York City, Audiophile is the premier store for high end headphones, earphones, speakers, and audio accessories. We have a large showroom and luxury demonstration rooms available for you to browse and experience a wide range of our products. Stop by our store to meet some of the fantastic people who make Audiophile the best place to buy your portable audio equipment.<\/p>"
      }
    }
  },
  "order": [
    "main-collection",
    "16484938648f5c52b0",
    "1648493869fde2feed"
  ]
}
